{
  "data_types": {
    "DECIMAL": {"snowflake": "NUMBER"},
    "DECIMAL(38,0)": {"snowflake": "NUMBER(38,0)"},
    "BIGINT": {"snowflake": "NUMBER(*,0)"},
    "INT": {"snowflake": "INT"},
    "SMALLINT": {"snowflake": "SMALLINT"},
    "TINYINT": {"snowflake": "TINYINT"},
    "DOUBLE": {"snowflake": "FLOAT"},
    "FLOAT": {"snowflake": "FLOAT4"},
    "STRING": {"snowflake": "VARCHAR(16777216)"},
    "BINARY": {"snowflake": "BINARY"},
    "BOOLEAN": {"snowflake": "BOOLEAN"},
    "DATE": {"snowflake": "DATE"},
    "TIMESTAMP": {"snowflake": "TIMESTAMP_LTZ"},
    "ARRAY<STRING>": {"snowflake": "ARRAY"},
    "MAP<STRING,STRING>": {"snowflake": "OBJECT"},
    "STRUCT": {"snowflake": "OBJECT"}
  },
  "unsupported_snowflake_features": [
    "EXTERNAL TABLES with Snowflake-specific file formats",
    "Snowflake Stages",
    "Snowflake Pipes",
    "Snowflake Streams",
    "Snowflake Tasks",
    "Snowflake Alerts",
    "Resource Monitors",
    "Network Policies",
    "Masking Policies",
    "Row Access Policies",
    "Tag-based governance",
    "Zero-copy cloning",
    "Time Travel (Databricks has time travel via Delta Lake versioning)",
    "Snowflake Search Optimization",
    "Clustering Keys (Databricks uses ZORDER)",
    "Automatic Clustering",
    "Snowflake Materialized Views (Delta Live Tables alternative)",
    "Dynamic Tables (Delta Live Tables alternative)",
    "Snowpark",
    "JavaScript UDFs",
    "Python UDFs",
    "Scala UDFs",
    "Java UDFs",
    "Snowflake SQL UDFs (convert to Databricks SQL UDFs or Python UDFs)",
    "External Functions",
    "Stored Procedures in JavaScript/Python/Scala/Java",
    "Snowflake-specific Context Functions (CURRENT_ACCOUNT, CURRENT_REGION, etc.)",
    "Snowflake-specific Session Functions (CURRENT_SESSION, CURRENT_TRANSACTION)",
    "GET_DDL",
    "SHOW commands (replace with INFORMATION_SCHEMA queries)",
    "DESCRIBE RESULT",
    "RESULT_SCAN",
    "Snowflake Information Schema with Snowflake-specific tables",
    "ACCOUNTADMIN, SYSADMIN roles (use Databricks workspace/admin roles)"
  ],
  "delta_lake_features": {
    "table_format": "DELTA",
    "optimization": "OPTIMIZE table ZORDER BY (column)",
    "vacuum": "VACUUM table RETAIN 168 HOURS",
    "history": "DESCRIBE HISTORY table",
    "details": "DESCRIBE DETAIL table",
    "merge": "MERGE INTO target USING source ON condition WHEN MATCHED THEN UPDATE SET ... WHEN NOT MATCHED THEN INSERT ...",
    "update": "UPDATE table SET column = value WHERE condition",
    "delete": "DELETE FROM table WHERE condition",
    "time_travel": "SELECT * FROM table VERSION AS OF version_number",
    "schema_evolution": "SET spark.databricks.delta.schema.autoMerge.enabled = true",
    "change_data_feed": "Requires Delta CDF to be enabled on the table"
  },
  "databricks_specific_syntax": {
    "create_table": "CREATE TABLE [IF NOT EXISTS] table_name (columns) USING DELTA [LOCATION path] [TBLPROPERTIES (props)]",
    "create_view": "CREATE [OR REPLACE] [TEMPORARY] VIEW [IF NOT EXISTS] view_name AS query",
    "create_function": "CREATE [OR REPLACE] FUNCTION [IF NOT EXISTS] function_name (params) RETURNS type [LANGUAGE SQL] AS 'body'",
    "merge_into": "MERGE INTO target t USING source s ON condition WHEN MATCHED THEN UPDATE SET ... WHEN NOT MATCHED THEN INSERT ...",
    "optimize": "OPTIMIZE table_name [ZORDER BY (col1, col2)]",
    "vacuum": "VACUUM table_name [RETAIN num HOURS]",
    "set_variable": "SET variable.name = value",
    "use_database": "USE database_name",
    "use_catalog": "USE CATALOG catalog_name",
    "create_schema": "CREATE SCHEMA [IF NOT EXISTS] schema_name [COMMENT 'comment'] [LOCATION path]",
    "create_catalog": "CREATE CATALOG [IF NOT EXISTS] catalog_name [COMMENT 'comment']"
  },
  "sql_conversion_rules": [
    {"snowflake": "QUALIFY ROW_NUMBER() OVER (PARTITION BY {cols} ORDER BY {order}) = 1", "databricks": "SELECT * FROM (SELECT *, ROW_NUMBER() OVER (PARTITION BY {cols} ORDER BY {order}) AS rn) WHERE rn = 1"},
    {"snowflake": "IFF({cond}, {true}, {false})", "databricks": "CASE WHEN {cond} THEN {true} ELSE {false} END"},
    {"snowflake": "LATERAL FLATTEN(input => {expr})", "databricks": "LATERAL VIEW EXPLODE({expr})"},
    {"snowflake": "ARRAY_AGG({expr})", "databricks": "COLLECT_LIST({expr})"},
    {"snowflake": "OBJECT_CONSTRUCT({k1}, {v1}, {k2}, {v2})", "databricks": "NAMED_STRUCT('{k1}', {v1}, '{k2}', {v2})"},
    {"snowflake": "LISTAGG({expr}, {delim})", "databricks": "CONCAT_WS({delim}, COLLECT_LIST({expr}))"},
    {"snowflake": "ZEROIFNULL({expr})", "databricks": "COALESCE({expr}, 0)"},
    {"snowflake": "NULLIFZERO({expr})", "databricks": "IF({expr} = 0, NULL, {expr})"},
    {"snowflake": "TO_VARCHAR({expr})", "databricks": "CAST({expr} AS STRING)"},
    {"snowflake": "TO_NUMBER({expr})", "databricks": "CAST({expr} AS DECIMAL)"},
    {"snowflake": "TO_BOOLEAN({expr})", "databricks": "CAST({expr} AS BOOLEAN)"},
    {"snowflake": "TO_ARRAY({expr})", "databricks": "ARRAY({expr})"},
    {"snowflake": "PARSE_JSON({expr})", "databricks": "FROM_JSON({expr}, 'schema')"},
    {"snowflake": "ARRAY_SIZE({expr})", "databricks": "SIZE({expr})"},
    {"snowflake": "GET({obj}, {key})", "databricks": "{obj}[{key}]"},
    {"snowflake": "RANDOM()", "databricks": "RAND()"},
    {"snowflake": "DATEADD({unit}, {val}, {date})", "databricks": "DATE_ADD({date}, {val})"},
    {"snowflake": "MONTHNAME({date})", "databricks": "DATE_FORMAT({date}, 'MMM')"},
    {"snowflake": "DAYNAME({date})", "databricks": "DATE_FORMAT({date}, 'EEE')"},
    {"snowflake": "FLATTEN({expr})", "databricks": "EXPLODE({expr})"}
  ]
}
